adleastcli.py
adleastcli-0.0.2.data/scripts/adleastcli
adleastcli-0.0.2.dist-info/LICENSE
adleastcli-0.0.2.dist-info/METADATA
adleastcli-0.0.2.dist-info/WHEEL
adleastcli-0.0.2.dist-info/top_level.txt
adleastcli-0.0.2.dist-info/RECORD
