Metadata-Version: 2.1
Name: adleastcli
Version: 0.0.2
Summary: Simple user management CLI for Active Directory
Home-page: https://github.com/nobrin/adleastcli
Author: Nobuo Okazaki
Author-email: nobrin@biokids.org
License: MIT
Platform: any
Classifier: Development Status :: 3 - Alpha
Classifier: Intended Audience :: System Administrators
Classifier: License :: OSI Approved :: MIT License
Classifier: Topic :: System :: Systems Administration :: Authentication/Directory :: LDAP
Classifier: Topic :: Software Development :: Libraries :: Python Modules
Classifier: Programming Language :: Python :: 2
Classifier: Programming Language :: Python :: 2.7
Classifier: Programming Language :: Python :: 3
Classifier: Programming Language :: Python :: 3.6
Classifier: Programming Language :: Python :: 3.7
Requires-Dist: ldap3
